CHANGES.txt
LICENSE.txt
setup.cfg
setup.py
zgeo.geographer-configure.zcml
zgeo/__init__.py
zgeo.geographer.egg-info/PKG-INFO
zgeo.geographer.egg-info/SOURCES.txt
zgeo.geographer.egg-info/dependency_links.txt
zgeo.geographer.egg-info/entry_points.txt
zgeo.geographer.egg-info/namespace_packages.txt
zgeo.geographer.egg-info/not-zip-safe
zgeo.geographer.egg-info/requires.txt
zgeo.geographer.egg-info/top_level.txt
zgeo/geographer/README.txt
zgeo/geographer/__init__.py
zgeo/geographer/configure.zcml
zgeo/geographer/event.py
zgeo/geographer/example.py
zgeo/geographer/geo.py
zgeo/geographer/interfaces.py
zgeo/geographer/tests.py
