Metadata-Version: 1.0
Name: zgeo.geographer
Version: 0.3.1
Summary: Geographic annotation for Zope
Home-page: http://trac.gispython.org/projects/PrimaGIS/wiki/zgeo.geographer
Author: Sean Gillies
Author-email: sgillies@frii.com
License: BSD
Keywords: gis geography geospatial
Platform: UNKNOWN
Classifier: Framework :: Plone
Classifier: Framework :: Zope3
Classifier: Programming Language :: Python
Classifier: Topic :: Software Development :: Libraries :: Python Modules
Classifier: Topic :: Scientific/Engineering :: GIS
Classifier: Development Status :: 3 - Alpha
Classifier: Intended Audience :: Developers
Classifier: License :: OSI Approved :: BSD License
